pdf2gif/__init__.py
pdf2gif/cli.py
pdf2gif-0.1.0.dist-info/licenses/LICENSE
pdf2gif-0.1.0.dist-info/METADATA
pdf2gif-0.1.0.dist-info/WHEEL
pdf2gif-0.1.0.dist-info/entry_points.txt
pdf2gif-0.1.0.dist-info/top_level.txt
pdf2gif-0.1.0.dist-info/RECORD
