Metadata-Version: 2.4
Name: pdf2gif
Version: 0.1.0
Summary: Convert PDF files to animated GIFs
Author-email: Robert Haase <robert.haase@uni-leipzig.de>
License: BSD-3
Project-URL: Homepage, https://github.com/haesleinhuepf/pdf2gif
Project-URL: Documentation, https://github.com/haesleinhuepf/pdf2gif#readme
Project-URL: Repository, https://github.com/haesleinhuepf/pdf2gif.git
Project-URL: Bug Tracker, https://github.com/haesleinhuepf/pdf2gif/issues
Keywords: pdf,gif,converter,animation,image
Classifier: Development Status :: 2 - Pre-Alpha
Classifier: Intended Audience :: Developers
Classifier: Intended Audience :: End Users/Desktop
Classifier: License :: OSI Approved :: BSD License
Classifier: Operating System :: OS Independent
Classifier: Programming Language :: Python :: 3
Classifier: Programming Language :: Python :: 3.9
Classifier: Programming Language :: Python :: 3.10
Classifier: Programming Language :: Python :: 3.11
Classifier: Programming Language :: Python :: 3.12
Classifier: Topic :: Multimedia :: Graphics :: Graphics Conversion
Classifier: Topic :: Scientific/Engineering :: Image Processing
Requires-Python: >=3.9
License-File: LICENSE
Requires-Dist: pdf2image
Requires-Dist: numpy
Requires-Dist: stackview
Requires-Dist: Pillow
Dynamic: license-file
